robust_vmaf/__init__.py
robust_vmaf/robust_vmaf.py
robust_vmaf/common/__init__.py
robust_vmaf/common/extractor.py
robust_vmaf/common/model.py
robust_vmaf/common/neural_model.py
robust_vmaf/common/utils.py
robust_vmaf/models/__init__.py
robust_vmaf/models/base_model.pkl
robust_vmaf/models/base_neg_model.pkl
robust_vmaf/models/neg_model.pkl
robust_vmaf-0.1.0.dev3.dist-info/LICENSE
robust_vmaf-0.1.0.dev3.dist-info/METADATA
robust_vmaf-0.1.0.dev3.dist-info/WHEEL
robust_vmaf-0.1.0.dev3.dist-info/top_level.txt
robust_vmaf-0.1.0.dev3.dist-info/RECORD
