Metadata-Version: 2.1
Name: robust-vmaf
Version: 0.1.0.dev3
Summary: robust modification of VMAF
Home-page: https://github.com/Hrebtovmaksim1/robust_vmaf
Author: Mg_det
Author-email: hrebtovmaksim1@gmail.com
License: UNKNOWN
Platform: UNKNOWN
Classifier: Programming Language :: Python :: 3
Classifier: License :: OSI Approved :: MIT License
Classifier: Operating System :: OS Independent
Requires-Python: >=3.6
License-File: LICENSE
Requires-Dist: numpy
Requires-Dist: pandas
Requires-Dist: scikit-learn
Requires-Dist: scipy
Requires-Dist: torch
Requires-Dist: tqdm
